newspaper3kli.py
lib/__init__.py
lib/http_client.py
newspaper3kli-0.1.1.data/data/UNLICENSE
newspaper3kli-0.1.1.dist-info/METADATA
newspaper3kli-0.1.1.dist-info/WHEEL
newspaper3kli-0.1.1.dist-info/entry_points.txt
newspaper3kli-0.1.1.dist-info/top_level.txt
newspaper3kli-0.1.1.dist-info/RECORD
